cliff_tablib-2.0.dist-info/DESCRIPTION.rst
cliff_tablib-2.0.dist-info/METADATA
cliff_tablib-2.0.dist-info/RECORD
cliff_tablib-2.0.dist-info/WHEEL
cliff_tablib-2.0.dist-info/entry_points.txt
cliff_tablib-2.0.dist-info/metadata.json
cliff_tablib-2.0.dist-info/namespace_packages.txt
cliff_tablib-2.0.dist-info/top_level.txt
clifftablib/__init__.py
clifftablib/formatters.py
